Workbook
Name Bancos: AUXILIAR!$A$12:$A$61
Name ListaCategorias: AUXILIAR!$A$2:$A$9

Sheet TITULAR
B2: LEÃO IR
B4: Seu apoio para declaração
B6: DADOS DO TITULAR
B7: NOME COMPLETO
B8: CPF
B9: DATA DE NASCIMENTO
B10: NOME DO CÔNJUGE
B11: DEPENDENTES
B14: INFORMAÇÕES DA DECLARAÇÃO
B15: ANO-CALENDÁRIO
B16: TIPO DE DECLARAÇÃO
B17: MODELO DE DECLARAÇÃO
... B26: "VALOR ESTIMADO. NÃO SE TRATA DE CÁLCULO OFICIAL DA RECEITA FEDERAL."

Sheet INFORMES
B2: LEÃO IR
B4: Seu apoio para declaração
B6: INFORMES DE RENDIMENTOS BANCÁRIOS
B8: 1º BANCO
B9: BANCO | D9: 1 - Banco do Brasil | F9: ANEXO
B10: VALOR ATUAL | D10: 1000 | F10: Anexar informe
B12: 2º BANCO
B13: BANCO | D13: 102 - XP Investimentos CCTVM S.A. | F13: ANEXO
B14: VALOR ATUAL | D14: 2000 | F14: Anexar informe
B16: 3º BANCO
B17: BANCO | D17: 212 - Banco Original | F17: ANEXO
B18: VALOR ATUAL | D18: 500 | F18: Anexar informe
B20: TOTAL | D20: =SUM(D10,D14,D18) -> 3500

Sheet NOTAS
B2: LEÃO IR
B4: Seu apoio para declaração
B6: NOTAS
B8: DATA | C8: CATEGORIA | D8: VALOR
B9: 45748 | C9: Salário / Holerite | D9: 3000 | E9: =VLOOKUP(C9,AUXILIAR!$A$2:$B$9,2,FALSE) -> Tributável
B10: 45762 | C10: Freelancer / Autônomo | D10: 500 | E10: =IF(C10="","",VLOOKUP(C10,AUXILIAR!$A$2:$B$9,2,FALSE)) -> Tributável
B11: 45767 | C11: Rendimentos isentos / não tributáveis | D11: 1000 | E11: =IF(C11="","",VLOOKUP(C11,AUXILIAR!$A$2:$B$9,2,FALSE)) -> Não tributável
B12: 45778 | C12: Salário / Holerite | D12: 1000 | E12: =IF(C12="","",VLOOKUP(C12,AUXILIAR!$A$2:$B$9,2,FALSE)) -> Tributável
E13: =IF(C13="","",VLOOKUP(C13,AUXILIAR!$A$2:$B$9,2,FALSE))
E14: =IF(C14="","",VLOOKUP(C14,AUXILIAR!$A$2:$B$9,2,FALSE))
E15: =IF(C15="","",VLOOKUP(C15,AUXILIAR!$A$2:$B$9,2,FALSE))
E16: =IF(C16="","",VLOOKUP(C16,AUXILIAR!$A$2:$B$9,2,FALSE))
E17: =IF(C17="","",VLOOKUP(C17,AUXILIAR!$A$2:$B$9,2,FALSE))
E18: =IF(C18="","",VLOOKUP(C18,AUXILIAR!$A$2:$B$9,2,FALSE))
E19: =IF(C19="","",VLOOKUP(C19,AUXILIAR!$A$2:$B$9,2,FALSE))
E20: =IF(C20="","",VLOOKUP(C20,AUXILIAR!$A$2:$B$9,2,FALSE))
E21: =IF(C21="","",VLOOKUP(C21,AUXILIAR!$A$2:$B$9,2,FALSE))
E22: =IF(C22="","",VLOOKUP(C22,AUXILIAR!$A$2:$B$9,2,FALSE))
E23: =IF(C23="","",VLOOKUP(C23,AUXILIAR!$A$2:$B$9,2,FALSE))
E24: =IF(C24="","",VLOOKUP(C24,AUXILIAR!$A$2:$B$9,2,FALSE))
... E28: =IF(C28="","",VLOOKUP(C28,AUXILIAR!$A$2:$B$9,2,FALSE))
B30: TOTAL DE RENDIMENTOS | D30: =SUM(D9:D28) -> 5500
B32: RENDA TRIBUTÁVEL | D32: =SUMIF(E9:E28,"Tributável",D9:D28) -> 4500
B34: DEDUÇÕES | D34: 500
B36: BASE DE CÁLCULO | D36: =D32-D34 -> 4000
B38: IMPOSTO DEVIDO | D38: =IF(D36<=28467.2,0,IF(D36<=33919.8,D36*7.5%-2135.04,IF(D36<=45012.6,D36*15%-4679.03,IF(D36<=55976.16,D36*22.5%-8054.97,D36*27.5%-10853.78)))) -> 0
B40: IR RETIDO NA FONTE | D40: 0
B42: =IF(D40>D38,"IMPOSTO A RESTITUIR",IF(D38>D40,"IMPOSTO A PAGAR","SEM IMPOSTO A PAGAR OU RESTITUIR")) -> SEM IMPOSTO A PAGAR OU RESTITUIR | D42: =IF(D40>D38,D40-D38,IF(D38>D40,D38-D40,0)) -> 0

Sheet AUXILIAR
A1: CATEGORIA | B1: CLASSIFICAÇÃO
A2: Salário / Holerite | B2: Tributável
A3: Freelancer / Autônomo | B3: Tributável
A4: Pró-labore | B4: Tributável
A5: Aluguel | B5: Tributável
A6: Aposentadoria / Pensão | B6: Tributável
A7: Rendimentos de investimentos | B7: Específico
A8: Rendimentos isentos / não tributáveis | B8: Não tributável
A9: Outros rendimentos | B9: Não classificado
A11: BANCOS
A12: 1 - Banco do Brasil
A13: 102 - XP Investimentos CCTVM S.A.
A14: 104 - Caixa Econômica Federal
A15: 119 - Banco Western Union do Brasil
A16: 184 - Banco Itaú BBA S.A.
A17: 197 - Stone Pagamentos
A18: 208 - Banco BTG Pactual
A19: 212 - Banco Original
A20: 218 - Banco Bonsucesso
A21: 229 - Banco Cruzeiro do Sul
A22: 237 - Banco Bradesco
... A61: 82 - Banco Topázio
